fmi_scheme/__init__.py
fmi_scheme/fmi1/fmiBaseUnit.xsd
fmi_scheme/fmi1/fmiImplementation.xsd
fmi_scheme/fmi1/fmiModelDescription.xsd
fmi_scheme/fmi1/fmiScalarVariable.xsd
fmi_scheme/fmi1/fmiType.xsd
fmi_scheme/fmi2/fmi2Annotation.xsd
fmi_scheme/fmi2/fmi2AttributeGroups.xsd
fmi_scheme/fmi2/fmi2ModelDescription.xsd
fmi_scheme/fmi2/fmi2ScalarVariable.xsd
fmi_scheme/fmi2/fmi2Type.xsd
fmi_scheme/fmi2/fmi2Unit.xsd
fmi_scheme/fmi2/fmi2VariableDependency.xsd
fmi_scheme/fmi3/fmi3Annotation.xsd
fmi_scheme/fmi3/fmi3AttributeGroups.xsd
fmi_scheme/fmi3/fmi3BuildDescription.xsd
fmi_scheme/fmi3/fmi3InterfaceType.xsd
fmi_scheme/fmi3/fmi3ModelDescription.xsd
fmi_scheme/fmi3/fmi3Terminal.xsd
fmi_scheme/fmi3/fmi3TerminalsAndIcons.xsd
fmi_scheme/fmi3/fmi3Type.xsd
fmi_scheme/fmi3/fmi3Unit.xsd
fmi_scheme/fmi3/fmi3Variable.xsd
fmi_scheme/fmi3/fmi3VariableDependency.xsd
osp_cosim/__init__.py
osp_cosim/linux/bin/cosim
osp_cosim/linux/bin/proxyfmu
osp_cosim/linux/bin/proxyfmu_booter
osp_cosim/linux/doc/LICENSE
osp_cosim/linux/doc/README.md
osp_cosim/linux/doc/licenses/boost/LICENSE_1_0.txt
osp_cosim/linux/doc/licenses/bzip2/LICENSE
osp_cosim/linux/doc/licenses/fmilibrary/FMILIB_Acknowledgements.txt
osp_cosim/linux/doc/licenses/fmilibrary/LICENSE.md
osp_cosim/linux/doc/licenses/libbacktrace/LICENSE
osp_cosim/linux/doc/licenses/libcosim/LICENSE
osp_cosim/linux/doc/licenses/libevent/LICENSE
osp_cosim/linux/doc/licenses/libzip/LICENSE
osp_cosim/linux/doc/licenses/ms-gsl/LICENSE
osp_cosim/linux/doc/licenses/openssl/LICENSE
osp_cosim/linux/doc/licenses/thrift/LICENSE
osp_cosim/linux/doc/licenses/xerces-c/LICENSE
osp_cosim/linux/doc/licenses/xerces-c/NOTICE
osp_cosim/linux/doc/licenses/xz_utils/COPYING
osp_cosim/linux/doc/licenses/yaml-cpp/LICENSE
osp_cosim/linux/doc/licenses/zlib/LICENSE
osp_cosim/linux/doc/licenses/zstd/LICENSE
osp_cosim/win64/bin/boost_atomic.dll
osp_cosim/win64/bin/boost_chrono.dll
osp_cosim/win64/bin/boost_context.dll
osp_cosim/win64/bin/boost_date_time.dll
pycosim-0.6.5.dist-info/LICENSE
pycosim-0.6.5.dist-info/METADATA
pycosim-0.6.5.dist-info/WHEEL
pycosim-0.6.5.dist-info/entry_points.txt
pycosim-0.6.5.dist-info/top_level.txt
pycosim-0.6.5.dist-info/RECORD
