Metadata-Version: 2.1
Name: pycosim
Version: 0.6.5
Summary: A python library to configure and run co-simulation using OSP software and standard
Home-page: https://github.com/kevinksyTRD/pycosim
Author: Kevin Koosup Yum
Author-email: kevinkoosup.yum@sintef.no
License: MIT License
Keywords: nbdev jupyter notebook python
Classifier: Development Status :: 4 - Beta
Classifier: Intended Audience :: Developers
Classifier: Natural Language :: English
Classifier: Programming Language :: Python :: 3.8
Classifier: Programming Language :: Python :: 3.9
Classifier: Programming Language :: Python :: 3.10
Classifier: License :: OSI Approved :: MIT License
Requires-Python: >=3.8
License-File: LICENSE
Requires-Dist: pyyaml (==6.0)
Requires-Dist: pyOSPParser (==0.5.0)
Requires-Dist: pandas (==1.5.0)
Requires-Dist: numpy (==1.23.4)
Requires-Dist: xmlschema (==1.2.5)
Requires-Dist: attrs (==21.1.0)
Requires-Dist: lxml (==4.9.1)
Requires-Dist: lark (==1.1.3)
Provides-Extra: dev
